anybonett/NET.py
anyBoNett-0.0.8.dist-info/LICENSE
anyBoNett-0.0.8.dist-info/METADATA
anyBoNett-0.0.8.dist-info/WHEEL
anyBoNett-0.0.8.dist-info/top_level.txt
anyBoNett-0.0.8.dist-info/RECORD
