Metadata-Version: 2.1
Name: anyBoNett
Version: 0.0.8
Summary: uma biblioteca pra facilitar pesquisas
Author: AnyBoLIB
Author-email: bidjorys@gmail.com
License: MIT License
Keywords: ytl,anybonett,net,anybonet,
License-File: LICENSE
Requires-Dist: wikipedia
